sawtooth/__init__.py
sawtooth/sawtooth.py
sawtooth-0.1.0rc23.post1.dist-info/LICENSE
sawtooth-0.1.0rc23.post1.dist-info/WHEEL
sawtooth-0.1.0rc23.post1.dist-info/METADATA
sawtooth-0.1.0rc23.post1.dist-info/RECORD
