Metadata-Version: 2.1
Name: sawtooth
Version: 0.1.0rc23.post1
Summary: Sample Python Project for creating a new Python Module
Author-email: Curtis Maddalozzo <curtis@maddalozzo.ca>
Requires-Python: >=3.7
Classifier: Development Status :: 3 - Alpha
Classifier: Intended Audience :: Developers
Classifier: License :: OSI Approved :: MIT License
Classifier: Programming Language :: Python :: 3 :: Only
Classifier: Programming Language :: Python :: 3.7
Classifier: Programming Language :: Python :: 3.8
Classifier: Programming Language :: Python :: 3.9
Classifier: Programming Language :: Python :: 3.10
Requires-Dist: bandit[toml]==1.7.4 ; extra == "test"
Requires-Dist: black==22.* ; extra == "test"
Requires-Dist: check-manifest==0.48 ; extra == "test"
Requires-Dist: flake8-bugbear==22.10.27 ; extra == "test"
Requires-Dist: flake8-docstrings ; extra == "test"
Requires-Dist: flake8-formatter_junit_xml ; extra == "test"
Requires-Dist: flake8==5.* ; extra == "test"
Requires-Dist: pre-commit==2.20.0 ; extra == "test"
Requires-Dist: pylint==2.15.6 ; extra == "test"
Requires-Dist: pylint_junit ; extra == "test"
Requires-Dist: pytest-cov==4.0.0 ; extra == "test"
Requires-Dist: pytest-mock<3.10.1 ; extra == "test"
Requires-Dist: pytest-runner ; extra == "test"
Requires-Dist: pytest==7.2.0 ; extra == "test"
Requires-Dist: pytest-asyncio==0.18.3 ; extra == "test"
Requires-Dist: pytest-github-actions-annotate-failures ; extra == "test"
Requires-Dist: shellcheck-py==0.8.0.4 ; extra == "test"
Project-URL: Documentation, https://github.com/cmaddalozzo/sawtooth/tree/main#readme
Project-URL: Source, https://github.com/cmaddalozzo/sawtooth
Project-URL: Tracker, https://github.com/cmaddalozzo/sawtooth/issues
Provides-Extra: test
